pykodi/__init__.py
pykodi/kodi.py
pykodi-0.2.7.dist-info/LICENSE
pykodi-0.2.7.dist-info/METADATA
pykodi-0.2.7.dist-info/WHEEL
pykodi-0.2.7.dist-info/top_level.txt
pykodi-0.2.7.dist-info/RECORD
