Metadata-Version: 2.1
Name: pykodi
Version: 0.2.7
Summary: An async python interface for Kodi over JSON-RPC.
Home-page: https://github.com/OnFreund/PyKodi
Author: On Freund
Author-email: onfreund@gmail.com
License: MIT
Platform: UNKNOWN
Classifier: License :: OSI Approved :: MIT License
Classifier: Programming Language :: Python
Classifier: Programming Language :: Python :: 3
Classifier: Programming Language :: Python :: 3.7
Classifier: Programming Language :: Python :: Implementation :: CPython
Classifier: Programming Language :: Python :: Implementation :: PyPy
Requires-Python: >=3.7.0
License-File: LICENSE
